<?xml version="1.0" encoding="UTF-8"?>

<!-- generated on Sun Oct 21 14:56:53 2018 by Eclipse SUMO Version 1.0.1
<configuration xmlns:xsi="http://www.w3.org/2001/XMLSchema-instance" xsi:noNamespaceSchemaLocation="http://sumo.dlr.de/xsd/sumoConfiguration.xsd">

    <input>
        <net-file value="Data/State_Street_4500_South.net.xml"/>
        <route-files value="Data/State_Street_4500_South.rou.xml"/>
        <additional-files value="Data/State_Street_4500_South.det.xml"/>
    </input>

    <output>
        <tripinfo-output value="tripinfo.xml"/>
    </output>

    <time>
        <begin value="0"/>
    </time>

    <processing>
        <time-to-teleport value="-1"/>
    </processing>

    <report>
        <verbose value="true"/>
        <no-step-log value="true"/>
    </report>

    <traci_server>
        <remote-port value="51269"/>
    </traci_server>

    <gui_only>
        <gui-settings-file value="Data/State_Street_4500_South.settings.xml"/>
    </gui_only>

</configuration>
-->

<detector xmlns:xsi="http://www.w3.org/2001/XMLSchema-instance" xsi:noNamespaceSchemaLocation="http://sumo.dlr.de/xsd/det_e2_file.xsd">
   <interval begin="0.00" end="100.00" id="laneAreaDetector.E1" sampledSeconds="18.42" nVehEntered="2" nVehLeft="1" nVehSeen="2" meanSpeed="3.32" meanTimeLoss="7.07" meanOccupancy="0.45" maxOccupancy="2.50" meanMaxJamLengthInVehicles="0.12" meanMaxJamLengthInMeters="0.60" maxJamLengthInVehicles="1" maxJamLengthInMeters="5.00" jamLengthInVehiclesSum="12" jamLengthInMetersSum="60.00" meanHaltingDuration="13.00" maxHaltingDuration="13.00" haltingDurationSum="13.00" meanIntervalHaltingDuration="13.00" maxIntervalHaltingDuration="13.00" intervalHaltingDurationSum="13.00" startedHalts="1.00" meanVehicleNumber="0.19" maxVehicleNumber="1" />
   <interval begin="100.00" end="200.00" id="laneAreaDetector.E1" sampledSeconds="30.84" nVehEntered="1" nVehLeft="1" nVehSeen="2" meanSpeed="0.97" meanTimeLoss="14.34" meanOccupancy="0.73" maxOccupancy="2.50" meanMaxJamLengthInVehicles="0.25" meanMaxJamLengthInMeters="1.24" maxJamLengthInVehicles="1" maxJamLengthInMeters="5.00" jamLengthInVehiclesSum="25" jamLengthInMetersSum="124.00" meanHaltingDuration="19.50" maxHaltingDuration="35.00" haltingDurationSum="39.00" meanIntervalHaltingDuration="13.00" maxIntervalHaltingDuration="22.00" intervalHaltingDurationSum="26.00" startedHalts="1.00" meanVehicleNumber="0.31" maxVehicleNumber="1" />
   <interval begin="200.00" end="300.00" id="laneAreaDetector.E1" sampledSeconds="100.96" nVehEntered="5" nVehLeft="5" nVehSeen="6" meanSpeed="1.14" meanTimeLoss="15.41" meanOccupancy="2.40" maxOccupancy="5.00" meanMaxJamLengthInVehicles="0.77" meanMaxJamLengthInMeters="3.88" maxJamLengthInVehicles="2" maxJamLengthInMeters="13.76" jamLengthInVehiclesSum="77" jamLengthInMetersSum="388.29" meanHaltingDuration="17.00" maxHaltingDuration="37.00" haltingDurationSum="85.00" meanIntervalHaltingDuration="16.20" maxIntervalHaltingDuration="37.00" intervalHaltingDurationSum="81.00" startedHalts="4.00" meanVehicleNumber="1.02" maxVehicleNumber="3" />
   <interval begin="300.00" end="400.00" id="laneAreaDetector.E1" sampledSeconds="92.15" nVehEntered="5" nVehLeft="5" nVehSeen="6" meanSpeed="0.75" meanTimeLoss="14.54" meanOccupancy="2.22" maxOccupancy="5.00" meanMaxJamLengthInVehicles="0.74" meanMaxJamLengthInMeters="3.69" maxJamLengthInVehicles="1" maxJamLengthInMeters="5.00" jamLengthInVehiclesSum="74" jamLengthInMetersSum="368.89" meanHaltingDuration="21.25" maxHaltingDuration="36.00" haltingDurationSum="85.00" meanIntervalHaltingDuration="19.25" maxIntervalHaltingDuration="36.00" intervalHaltingDurationSum="77.00" startedHalts="3.00" meanVehicleNumber="0.94" maxVehicleNumber="2" />
   <interval begin="400.00" end="500.00" id="laneAreaDetector.E1" sampledSeconds="165.57" nVehEntered="5" nVehLeft="5" nVehSeen="6" meanSpeed="0.54" meanTimeLoss="26.45" meanOccupancy="4.02" maxOccupancy="7.50" meanMaxJamLengthInVehicles="1.36" meanMaxJamLengthInMeters="8.13" maxJamLengthInVehicles="2" maxJamLengthInMeters="13.98" jamLengthInVehiclesSum="136" jamLengthInMetersSum="813.00" meanHaltingDuration="22.86" maxHaltingDuration="36.00" haltingDurationSum="160.00" meanIntervalHaltingDuration="20.29" maxIntervalHaltingDuration="36.00" intervalHaltingDurationSum="142.00" startedHalts="6.00" meanVehicleNumber="1.67" maxVehicleNumber="3" />
   <interval begin="500.00" end="600.00" id="laneAreaDetector.E1" sampledSeconds="48.72" nVehEntered="1" nVehLeft="1" nVehSeen="2" meanSpeed="0.61" meanTimeLoss="23.21" meanOccupancy="1.18" maxOccupancy="2.50" meanMaxJamLengthInVehicles="0.43" meanMaxJamLengthInMeters="2.14" maxJamLengthInVehicles="1" maxJamLengthInMeters="5.00" jamLengthInVehiclesSum="43" jamLengthInMetersSum="213.97" meanHaltingDuration="29.00" maxHaltingDuration="36.00" haltingDurationSum="58.00" meanIntervalHaltingDuration="22.00" maxIntervalHaltingDuration="22.00" intervalHaltingDurationSum="44.00" startedHalts="1.00" meanVehicleNumber="0.49" maxVehicleNumber="1" />
   <interval begin="600.00" end="700.00" id="laneAreaDetector.E1" sampledSeconds="89.75" nVehEntered="7" nVehLeft="6" nVehSeen="8" meanSpeed="1.78" meanTimeLoss="9.84" meanOccupancy="2.12" maxOccupancy="5.00" meanMaxJamLengthInVehicles="0.58" meanMaxJamLengthInMeters="2.95" maxJamLengthInVehicles="2" maxJamLengthInMeters="13.87" jamLengthInVehiclesSum="58" jamLengthInMetersSum="295.47" meanHaltingDuration="14.17" maxHaltingDuration="30.00" haltingDurationSum="85.00" meanIntervalHaltingDuration="10.50" maxIntervalHaltingDuration="30.00" intervalHaltingDurationSum="63.00" startedHalts="5.00" meanVehicleNumber="0.91" maxVehicleNumber="3" />
   <interval begin="700.00" end="800.00" id="laneAreaDetector.E1" sampledSeconds="243.11" nVehEntered="4" nVehLeft="4" nVehSeen="6" meanSpeed="0.56" meanTimeLoss="38.88" meanOccupancy="6.00" maxOccupancy="8.11" meanMaxJamLengthInVehicles="2.14" meanMaxJamLengthInMeters="13.72" maxJamLengthInVehicles="3" maxJamLengthInMeters="22.53" jamLengthInVehiclesSum="214" jamLengthInMetersSum="1371.51" meanHaltingDuration="29.50" maxHaltingDuration="37.00" haltingDurationSum="236.00" meanIntervalHaltingDuration="27.50" maxIntervalHaltingDuration="36.00" intervalHaltingDurationSum="220.00" startedHalts="6.00" meanVehicleNumber="2.44" maxVehicleNumber="4" />
   <interval begin="800.00" end="900.00" id="laneAreaDetector.E1" sampledSeconds="122.73" nVehEntered="3" nVehLeft="5" nVehSeen="5" meanSpeed="0.58" meanTimeLoss="23.48" meanOccupancy="2.95" maxOccupancy="7.50" meanMaxJamLengthInVehicles="1.03" meanMaxJamLengthInMeters="5.91" maxJamLengthInVehicles="2" maxJamLengthInMeters="13.94" jamLengthInVehiclesSum="103" jamLengthInMetersSum="590.50" meanHaltingDuration="34.80" maxHaltingDuration="37.00" haltingDurationSum="174.00" meanIntervalHaltingDuration="21.20" maxIntervalHaltingDuration="36.00" intervalHaltingDurationSum="106.00" startedHalts="3.00" meanVehicleNumber="1.24" maxVehicleNumber="3" />
   <interval begin="900.00" end="1000.00" id="laneAreaDetector.E1" sampledSeconds="105.55" nVehEntered="7" nVehLeft="5" nVehSeen="7" meanSpeed="0.83" meanTimeLoss="14.16" meanOccupancy="2.56" maxOccupancy="7.50" meanMaxJamLengthInVehicles="0.83" meanMaxJamLengthInMeters="4.33" maxJamLengthInVehicles="2" maxJamLengthInMeters="12.50" jamLengthInVehiclesSum="83" jamLengthInMetersSum="432.93" meanHaltingDuration="17.60" maxHaltingDuration="36.00" haltingDurationSum="88.00" meanIntervalHaltingDuration="17.60" maxIntervalHaltingDuration="36.00" intervalHaltingDurationSum="88.00" startedHalts="5.00" meanVehicleNumber="1.06" maxVehicleNumber="3" />
   <interval begin="1000.00" end="1100.00" id="laneAreaDetector.E1" sampledSeconds="207.89" nVehEntered="6" nVehLeft="7" nVehSeen="8" meanSpeed="0.69" meanTimeLoss="24.69" meanOccupancy="5.07" maxOccupancy="7.50" meanMaxJamLengthInVehicles="1.71" meanMaxJamLengthInMeters="10.65" maxJamLengthInVehicles="3" maxJamLengthInMeters="21.70" jamLengthInVehiclesSum="171" jamLengthInMetersSum="1064.88" meanHaltingDuration="26.62" maxHaltingDuration="36.00" haltingDurationSum="213.00" meanIntervalHaltingDuration="21.25" maxIntervalHaltingDuration="36.00" intervalHaltingDurationSum="170.00" startedHalts="7.00" meanVehicleNumber="2.09" maxVehicleNumber="4" />
   <interval begin="1100.00" end="1200.00" id="laneAreaDetector.E1" sampledSeconds="261.82" nVehEntered="8" nVehLeft="6" nVehSeen="9" meanSpeed="1.11" meanTimeLoss="26.78" meanOccupancy="6.46" maxOccupancy="10.00" meanMaxJamLengthInVehicles="2.11" meanMaxJamLengthInMeters="13.52" maxJamLengthInVehicles="3" maxJamLengthInMeters="21.71" jamLengthInVehiclesSum="211" jamLengthInMetersSum="1351.93" meanHaltingDuration="24.22" maxHaltingDuration="37.00" haltingDurationSum="218.00" meanIntervalHaltingDuration="22.67" maxIntervalHaltingDuration="37.00" intervalHaltingDurationSum="204.00" startedHalts="9.00" meanVehicleNumber="2.62" maxVehicleNumber="4" />
   <interval begin="1200.00" end="1300.00" id="laneAreaDetector.E1" sampledSeconds="292.93" nVehEntered="6" nVehLeft="6" nVehSeen="9" meanSpeed="0.43" meanTimeLoss="31.56" meanOccupancy="7.20" maxOccupancy="10.00" meanMaxJamLengthInVehicles="2.46" meanMaxJamLengthInMeters="16.27" maxJamLengthInVehicles="4" maxJamLengthInMeters="29.28" jamLengthInVehiclesSum="246" jamLengthInMetersSum="1627.39" meanHaltingDuration="25.15" maxHaltingDuration="36.00" haltingDurationSum="327.00" meanIntervalHaltingDuration="19.69" maxIntervalHaltingDuration="36.00" intervalHaltingDurationSum="256.00" startedHalts="10.00" meanVehicleNumber="2.94" maxVehicleNumber="4" />
   <interval begin="1300.00" end="1400.00" id="laneAreaDetector.E1" sampledSeconds="437.70" nVehEntered="11" nVehLeft="7" nVehSeen="14" meanSpeed="0.84" meanTimeLoss="29.28" meanOccupancy="10.86" maxOccupancy="17.50" meanMaxJamLengthInVehicles="3.68" meanMaxJamLengthInMeters="25.27" maxJamLengthInVehicles="7" maxJamLengthInMeters="50.01" jamLengthInVehiclesSum="368" jamLengthInMetersSum="2527.21" meanHaltingDuration="27.93" maxHaltingDuration="37.00" haltingDurationSum="419.00" meanIntervalHaltingDuration="25.33" maxIntervalHaltingDuration="37.00" intervalHaltingDurationSum="380.00" startedHalts="12.00" meanVehicleNumber="4.38" maxVehicleNumber="7" />
   <interval begin="1400.00" end="1500.00" id="laneAreaDetector.E1" sampledSeconds="605.86" nVehEntered="7" nVehLeft="8" nVehSeen="14" meanSpeed="0.60" meanTimeLoss="41.41" meanOccupancy="15.03" maxOccupancy="17.50" meanMaxJamLengthInVehicles="4.98" meanMaxJamLengthInMeters="35.33" maxJamLengthInVehicles="7" maxJamLengthInMeters="51.56" jamLengthInVehiclesSum="505" jamLengthInMetersSum="3571.02" meanHaltingDuration="25.30" maxHaltingDuration="37.00" haltingDurationSum="683.00" meanIntervalHaltingDuration="18.74" maxIntervalHaltingDuration="37.00" intervalHaltingDurationSum="506.00" startedHalts="22.00" meanVehicleNumber="6.08" maxVehicleNumber="7" />
   <interval begin="1500.00" end="1600.00" id="laneAreaDetector.E1" sampledSeconds="606.71" nVehEntered="7" nVehLeft="5" nVehSeen="13" meanSpeed="0.52" meanTimeLoss="44.86" meanOccupancy="15.09" maxOccupancy="20.00" meanMaxJamLengthInVehicles="5.35" meanMaxJamLengthInMeters="37.80" maxJamLengthInVehicles="7" maxJamLengthInMeters="50.01" jamLengthInVehiclesSum="538" jamLengthInMetersSum="3794.61" meanHaltingDuration="32.42" maxHaltingDuration="37.00" haltingDurationSum="616.00" meanIntervalHaltingDuration="29.00" maxIntervalHaltingDuration="37.00" intervalHaltingDurationSum="551.00" startedHalts="13.00" meanVehicleNumber="6.07" maxVehicleNumber="8" />
   <interval begin="1600.00" end="1700.00" id="laneAreaDetector.E1" sampledSeconds="621.21" nVehEntered="5" nVehLeft="7" nVehSeen="13" meanSpeed="0.40" meanTimeLoss="46.38" meanOccupancy="15.41" maxOccupancy="20.00" meanMaxJamLengthInVehicles="5.30" meanMaxJamLengthInMeters="37.62" maxJamLengthInVehicles="7" maxJamLengthInMeters="50.74" jamLengthInVehiclesSum="539" jamLengthInMetersSum="3809.35" meanHaltingDuration="27.81" maxHaltingDuration="37.00" haltingDurationSum="723.00" meanIntervalHaltingDuration="20.31" maxIntervalHaltingDuration="37.00" intervalHaltingDurationSum="528.00" startedHalts="20.00" meanVehicleNumber="6.22" maxVehicleNumber="8" />
   <interval begin="1700.00" end="1800.00" id="laneAreaDetector.E1" sampledSeconds="603.33" nVehEntered="4" nVehLeft="4" nVehSeen="10" meanSpeed="0.34" meanTimeLoss="58.88" meanOccupancy="15.00" maxOccupancy="17.50" meanMaxJamLengthInVehicles="5.44" meanMaxJamLengthInMeters="38.57" maxJamLengthInVehicles="7" maxJamLengthInMeters="51.80" jamLengthInVehiclesSum="549" jamLengthInMetersSum="3885.00" meanHaltingDuration="33.21" maxHaltingDuration="38.00" haltingDurationSum="631.00" meanIntervalHaltingDuration="29.58" maxIntervalHaltingDuration="37.00" intervalHaltingDurationSum="562.00" startedHalts="13.00" meanVehicleNumber="6.05" maxVehicleNumber="7" />
   <interval begin="1800.00" end="1900.00" id="laneAreaDetector.E1" sampledSeconds="504.87" nVehEntered="3" nVehLeft="5" nVehSeen="9" meanSpeed="0.39" meanTimeLoss="54.65" meanOccupancy="12.50" maxOccupancy="17.50" meanMaxJamLengthInVehicles="4.34" meanMaxJamLengthInMeters="30.35" maxJamLengthInVehicles="6" maxJamLengthInMeters="44.33" jamLengthInVehiclesSum="438" jamLengthInMetersSum="3055.34" meanHaltingDuration="28.41" maxHaltingDuration="37.00" haltingDurationSum="625.00" meanIntervalHaltingDuration="20.64" maxIntervalHaltingDuration="37.00" intervalHaltingDurationSum="454.00" startedHalts="16.00" meanVehicleNumber="5.07" maxVehicleNumber="7" />
   <interval begin="1900.00" end="2000.00" id="laneAreaDetector.E1" sampledSeconds="556.60" nVehEntered="9" nVehLeft="6" nVehSeen="13" meanSpeed="0.54" meanTimeLoss="41.16" meanOccupancy="13.84" maxOccupancy="17.50" meanMaxJamLengthInVehicles="4.84" meanMaxJamLengthInMeters="33.98" maxJamLengthInVehicles="7" maxJamLengthInMeters="50.04" jamLengthInVehiclesSum="486" jamLengthInMetersSum="3408.32" meanHaltingDuration="28.89" maxHaltingDuration="37.00" haltingDurationSum="549.00" meanIntervalHaltingDuration="26.37" maxIntervalHaltingDuration="37.00" intervalHaltingDurationSum="501.00" startedHalts="15.00" meanVehicleNumber="5.57" maxVehicleNumber="7" />
   <interval begin="2000.00" end="2100.00" id="laneAreaDetector.E1" sampledSeconds="672.97" nVehEntered="6" nVehLeft="6" nVehSeen="13" meanSpeed="0.50" meanTimeLoss="49.74" meanOccupancy="16.70" maxOccupancy="20.00" meanMaxJamLengthInVehicles="5.72" meanMaxJamLengthInMeters="40.82" maxJamLengthInVehicles="7" maxJamLengthInMeters="51.72" jamLengthInVehiclesSum="579" jamLengthInMetersSum="4119.20" meanHaltingDuration="28.04" maxHaltingDuration="37.00" haltingDurationSum="785.00" meanIntervalHaltingDuration="21.43" maxIntervalHaltingDuration="37.00" intervalHaltingDurationSum="600.00" startedHalts="21.00" meanVehicleNumber="6.74" maxVehicleNumber="8" />
   <interval begin="2100.00" end="2200.00" id="laneAreaDetector.E1" sampledSeconds="612.11" nVehEntered="3" nVehLeft="5" nVehSeen="10" meanSpeed="0.28" meanTimeLoss="59.90" meanOccupancy="15.22" maxOccupancy="20.00" meanMaxJamLengthInVehicles="5.49" meanMaxJamLengthInMeters="39.07" maxJamLengthInVehicles="7" maxJamLengthInMeters="51.75" jamLengthInVehiclesSum="553" jamLengthInMetersSum="3927.10" meanHaltingDuration="31.65" maxHaltingDuration="37.00" haltingDurationSum="633.00" meanIntervalHaltingDuration="28.00" maxIntervalHaltingDuration="37.00" intervalHaltingDurationSum="560.00" startedHalts="15.00" meanVehicleNumber="6.13" maxVehicleNumber="8" />
   <interval begin="2200.00" end="2300.00" id="laneAreaDetector.E1" sampledSeconds="598.41" nVehEntered="8" nVehLeft="7" nVehSeen="13" meanSpeed="0.40" meanTimeLoss="44.66" meanOccupancy="14.84" maxOccupancy="17.50" meanMaxJamLengthInVehicles="5.04" meanMaxJamLengthInMeters="35.66" maxJamLengthInVehicles="7" maxJamLengthInMeters="52.06" jamLengthInVehiclesSum="512" jamLengthInMetersSum="3606.01" meanHaltingDuration="26.35" maxHaltingDuration="37.00" haltingDurationSum="685.00" meanIntervalHaltingDuration="20.50" maxIntervalHaltingDuration="37.00" intervalHaltingDurationSum="533.00" startedHalts="21.00" meanVehicleNumber="5.99" maxVehicleNumber="8" />
   <interval begin="2300.00" end="2400.00" id="laneAreaDetector.E1" sampledSeconds="813.69" nVehEntered="11" nVehLeft="7" nVehSeen="17" meanSpeed="0.79" meanTimeLoss="45.09" meanOccupancy="20.26" maxOccupancy="25.00" meanMaxJamLengthInVehicles="6.93" meanMaxJamLengthInMeters="49.81" maxJamLengthInVehicles="10" maxJamLengthInMeters="72.54" jamLengthInVehiclesSum="703" jamLengthInMetersSum="5038.52" meanHaltingDuration="30.50" maxHaltingDuration="38.00" haltingDurationSum="793.00" meanIntervalHaltingDuration="27.81" maxIntervalHaltingDuration="37.00" intervalHaltingDurationSum="723.00" startedHalts="20.00" meanVehicleNumber="8.14" maxVehicleNumber="10" />
   <interval begin="2400.00" end="2500.00" id="laneAreaDetector.E1" sampledSeconds="1093.07" nVehEntered="10" nVehLeft="8" nVehSeen="20" meanSpeed="0.42" meanTimeLoss="52.95" meanOccupancy="27.21" maxOccupancy="30.00" meanMaxJamLengthInVehicles="8.93" meanMaxJamLengthInMeters="65.10" maxJamLengthInVehicles="12" maxJamLengthInMeters="88.92" jamLengthInVehiclesSum="952" jamLengthInMetersSum="6902.70" meanHaltingDuration="27.24" maxHaltingDuration="38.00" haltingDurationSum="1253.00" meanIntervalHaltingDuration="21.48" maxIntervalHaltingDuration="38.00" intervalHaltingDurationSum="988.00" startedHalts="36.00" meanVehicleNumber="10.95" maxVehicleNumber="12" />
   <interval begin="2500.00" end="2600.00" id="laneAreaDetector.E1" sampledSeconds="1126.62" nVehEntered="5" nVehLeft="5" nVehSeen="17" meanSpeed="0.24" meanTimeLoss="65.03" meanOccupancy="28.08" maxOccupancy="32.50" meanMaxJamLengthInVehicles="9.99" meanMaxJamLengthInMeters="72.96" maxJamLengthInVehicles="12" maxJamLengthInMeters="87.77" jamLengthInVehiclesSum="1036" jamLengthInMetersSum="7542.27" meanHaltingDuration="32.54" maxHaltingDuration="38.00" haltingDurationSum="1139.00" meanIntervalHaltingDuration="30.03" maxIntervalHaltingDuration="38.00" intervalHaltingDurationSum="1051.00" startedHalts="25.00" meanVehicleNumber="11.28" maxVehicleNumber="13" />
   <interval begin="2600.00" end="2700.00" id="laneAreaDetector.E1" sampledSeconds="1286.41" nVehEntered="10" nVehLeft="8" nVehSeen="22" meanSpeed="0.38" meanTimeLoss="56.76" meanOccupancy="32.04" maxOccupancy="35.00" meanMaxJamLengthInVehicles="10.45" meanMaxJamLengthInMeters="76.68" maxJamLengthInVehicles="13" maxJamLengthInMeters="96.64" jamLengthInVehiclesSum="1131" jamLengthInMetersSum="8249.81" meanHaltingDuration="27.72" maxHaltingDuration="38.00" haltingDurationSum="1497.00" meanIntervalHaltingDuration="21.72" maxIntervalHaltingDuration="38.00" intervalHaltingDurationSum="1173.00" startedHalts="42.00" meanVehicleNumber="12.89" maxVehicleNumber="14" />
   <interval begin="2700.00" end="2800.00" id="laneAreaDetector.E1" sampledSeconds="1482.69" nVehEntered="9" nVehLeft="8" nVehSeen="23" meanSpeed="0.25" meanTimeLoss="63.29" meanOccupancy="36.98" maxOccupancy="40.00" meanMaxJamLengthInVehicles="12.74" meanMaxJamLengthInMeters="93.86" maxJamLengthInVehicles="16" maxJamLengthInMeters="118.14" jamLengthInVehiclesSum="1355" jamLengthInMetersSum="9942.42" meanHaltingDuration="30.54" maxHaltingDuration="38.00" haltingDurationSum="1466.00" meanIntervalHaltingDuration="28.56" maxIntervalHaltingDuration="37.00" intervalHaltingDurationSum="1371.00" startedHalts="37.00" meanVehicleNumber="14.83" maxVehicleNumber="16" />
   <interval begin="2800.00" end="2900.00" id="laneAreaDetector.E1" sampledSeconds="1637.51" nVehEntered="9" nVehLeft="7" nVehSeen="24" meanSpeed="0.28" meanTimeLoss="66.78" meanOccupancy="40.81" maxOccupancy="45.00" meanMaxJamLengthInVehicles="13.07" meanMaxJamLengthInMeters="96.59" maxJamLengthInVehicles="17" maxJamLengthInMeters="126.92" jamLengthInVehiclesSum="1468" jamLengthInMetersSum="10791.68" meanHaltingDuration="28.92" maxHaltingDuration="38.00" haltingDurationSum="1909.00" meanIntervalHaltingDuration="23.02" maxIntervalHaltingDuration="38.00" intervalHaltingDurationSum="1519.00" startedHalts="51.00" meanVehicleNumber="16.40" maxVehicleNumber="18" />
   <interval begin="2900.00" end="3000.00" id="laneAreaDetector.E1" sampledSeconds="1837.04" nVehEntered="9" nVehLeft="7" nVehSeen="26" meanSpeed="0.23" meanTimeLoss="69.48" meanOccupancy="45.84" maxOccupancy="50.00" meanMaxJamLengthInVehicles="15.37" meanMaxJamLengthInMeters="113.72" maxJamLengthInVehicles="19" maxJamLengthInMeters="142.02" jamLengthInVehiclesSum="1693" jamLengthInMetersSum="12480.16" meanHaltingDuration="31.30" maxHaltingDuration="38.00" haltingDurationSum="1909.00" meanIntervalHaltingDuration="28.49" maxIntervalHaltingDuration="38.00" intervalHaltingDurationSum="1738.00" startedHalts="46.00" meanVehicleNumber="18.38" maxVehicleNumber="20" />
   <interval begin="3000.00" end="3021.00" id="laneAreaDetector.E1" sampledSeconds="401.36" nVehEntered="3" nVehLeft="2" nVehSeen="22" meanSpeed="0.49" meanTimeLoss="17.55" meanOccupancy="47.59" maxOccupancy="50.00" meanMaxJamLengthInVehicles="12.95" meanMaxJamLengthInMeters="95.98" maxJamLengthInVehicles="19" maxJamLengthInMeters="141.42" jamLengthInVehiclesSum="339" jamLengthInMetersSum="2492.25" meanHaltingDuration="23.35" maxHaltingDuration="37.00" haltingDurationSum="794.00" meanIntervalHaltingDuration="10.41" maxIntervalHaltingDuration="21.00" intervalHaltingDurationSum="354.00" startedHalts="15.00" meanVehicleNumber="19.14" maxVehicleNumber="20" />
</detector>
